Metadata-Version: 2.1
Name: sztutil
Version: 0.0.6
Summary: 深证通辅助工具
Home-page: https://gitee.com/chenc224/sztutil
Author: Chen chuan
Author-email: kcchen@139.com
License: UNKNOWN
Platform: UNKNOWN
Classifier: Programming Language :: Python :: 3
Classifier: License :: OSI Approved :: MIT License
Classifier: Operating System :: OS Independent
Requires-Python: >=3.5
